resolv3r/__init__.py
resolv3r-1.0.3.dist-info/LICENSE
resolv3r-1.0.3.dist-info/WHEEL
resolv3r-1.0.3.dist-info/METADATA
resolv3r-1.0.3.dist-info/RECORD
