Metadata-Version: 2.1
Name: resolv3r
Version: 1.0.3
Summary: A simple python package aimed at simplifying the vendor resolution process for network devices
Home-page: https://github.com/HullaBrian/resolv3r
Author: hullabrian
Requires-Python: >=3.8,<4.0
Classifier: Programming Language :: Python :: 3
Classifier: Programming Language :: Python :: 3.10
Classifier: Programming Language :: Python :: 3.8
Classifier: Programming Language :: Python :: 3.9
Requires-Dist: asyncssh (>=2.11.0,<3.0.0)
Requires-Dist: netmiko (>=4.1.1,<5.0.0)
